jupyterlab_resource_tracker/__init__.py
jupyterlab_resource_tracker/_version.py
jupyterlab_resource_tracker/handlers.py
jupyterlab_resource_tracker/logs_handler.py
jupyterlab_resource_tracker/labextension/build_log.json
jupyterlab_resource_tracker/labextension/package.json
jupyterlab_resource_tracker/labextension/schemas/jupyterlab-resource-tracker/package.json.orig
jupyterlab_resource_tracker/labextension/schemas/jupyterlab-resource-tracker/plugin.json
jupyterlab_resource_tracker/labextension/static/lib_index_js.4ebddb76005033198305.js
jupyterlab_resource_tracker/labextension/static/lib_index_js.4ebddb76005033198305.js.map
jupyterlab_resource_tracker/labextension/static/node_modules_emotion_use-insertion-effect-with-fallbacks_dist_emotion-use-insertion-effect-wi-3c9bb40.952a09e525d2cb5b6987.js
jupyterlab_resource_tracker/labextension/static/node_modules_emotion_use-insertion-effect-with-fallbacks_dist_emotion-use-insertion-effect-wi-3c9bb40.952a09e525d2cb5b6987.js.map
jupyterlab_resource_tracker/labextension/static/node_modules_emotion_use-insertion-effect-with-fallbacks_dist_emotion-use-insertion-effect-wi-3c9bb41.870413953004889f3ea8.js
jupyterlab_resource_tracker/labextension/static/node_modules_emotion_use-insertion-effect-with-fallbacks_dist_emotion-use-insertion-effect-wi-3c9bb41.870413953004889f3ea8.js.map
jupyterlab_resource_tracker/labextension/static/remoteEntry.2b4ecb5942f2bc297115.js
jupyterlab_resource_tracker/labextension/static/remoteEntry.2b4ecb5942f2bc297115.js.map
jupyterlab_resource_tracker/labextension/static/style.js
jupyterlab_resource_tracker/labextension/static/style_index_js.3c88ca6a7e2ed71f2db3.js
jupyterlab_resource_tracker/labextension/static/style_index_js.3c88ca6a7e2ed71f2db3.js.map
jupyterlab_resource_tracker/labextension/static/vendors-node_modules_emotion_cache_dist_emotion-cache_browser_development_esm_js.00a3fbbc34ee543dc161.js
jupyterlab_resource_tracker-0.2.22.dist-info/METADATA
jupyterlab_resource_tracker-0.2.22.dist-info/WHEEL
jupyterlab_resource_tracker-0.2.22.dist-info/licenses/LICENSE
jupyterlab_resource_tracker-0.2.22.dist-info/RECORD
